googlesearch/__init__.py
googlesearch_python_extended-2020.1.0.dist-info/METADATA
googlesearch_python_extended-2020.1.0.dist-info/WHEEL
googlesearch_python_extended-2020.1.0.dist-info/top_level.txt
googlesearch_python_extended-2020.1.0.dist-info/RECORD
