Metadata-Version: 2.1
Name: googlesearch-python-extended
Version: 2020.1.0
Summary: A Python library for scraping the Google search engine.
Home-page: https://github.com/dardem/googlesearch
Author: Daryna Dementieva, Nishant Vikramaditya
Author-email: dardem96@gmail.com
License: UNKNOWN
Platform: UNKNOWN
Classifier: Programming Language :: Python :: 3
Classifier: License :: OSI Approved :: MIT License
Classifier: Operating System :: OS Independent
Requires-Python: >=3.6
Requires-Dist: requests (==2.25.1)
Requires-Dist: beautifulsoup4 (==4.9.3)
